MANIFEST.in
README.md
setup.cfg
setup.py
bin/run-in-env-of
bin/run-in-gui
doc/bitcoin.png
run_in_gui.egg-info/PKG-INFO
run_in_gui.egg-info/SOURCES.txt
run_in_gui.egg-info/dependency_links.txt
run_in_gui.egg-info/not-zip-safe
run_in_gui.egg-info/top_level.txt
src/runingui/__init__.py