Metadata-Version: 1.1
Name: run-in-gui
Version: 0.0.1
Summary: Tools to run (possibly graphical) programs in logged-in user sessions on modern Linux distributions
Home-page: http://github.com/Rudd-O/run-in-gui
Author: Manuel Amador (Rudd-O)
Author-email: rudd-o@rudd-o.com
License: GPL
Keywords: cron loginctl daemon GUI
Platform: UNKNOWN
Classifier: Development Status :: 4 - Beta
Classifier: Environment :: Console
Classifier: Environment :: No Input/Output (Daemon)
Classifier: Intended Audience :: End Users/Desktop
Classifier: Intended Audience :: System Administrators
Classifier: License :: OSI Approved :: GNU General Public License (GPL)
Classifier: Operating System :: POSIX :: Linux
Classifier: Programming Language :: Python :: 2 :: Only
Classifier: Programming Language :: Python :: 2.7
